dirty_json/__init__.py
dirty_json/dirty_json.py
dirty_json/lexer.py
dirty_json/parser.py
dirty_json_py-0.1.0.dist-info/METADATA
dirty_json_py-0.1.0.dist-info/WHEEL
dirty_json_py-0.1.0.dist-info/RECORD
